lobster/__main__.py
lobster/_version.py
lobster/cli.py
lobster/main.py
lobster/version.py
lobster/agents/draw_graph.py
lobster/agents/graph.py
lobster/agents/state.py
lobster/agents/supervisor.py
lobster/agents/visualization_expert.py
lobster/agents/archive/research_agent_assistant.py
lobster/agents/data_expert/__init__.py
lobster/agents/data_expert/assistant.py
lobster/agents/data_expert/config.py
lobster/agents/data_expert/data_expert.py
lobster/agents/data_expert/prompts.py
lobster/agents/data_expert/state.py
lobster/agents/langgraph_supervisor/__init__.py
lobster/agents/langgraph_supervisor/agent_name.py
lobster/agents/langgraph_supervisor/handoff.py
lobster/agents/langgraph_supervisor/supervisor.py
lobster/agents/proteomics/__init__.py
lobster/agents/proteomics/state.py
lobster/agents/research/__init__.py
lobster/agents/research/config.py
lobster/agents/research/prompts.py
lobster/agents/research/research_agent.py
lobster/agents/research/state.py
lobster/agents/transcriptomics/__init__.py
lobster/agents/transcriptomics/annotation_expert.py
lobster/agents/transcriptomics/config.py
lobster/agents/transcriptomics/de_analysis_expert.py
lobster/agents/transcriptomics/prompts.py
lobster/agents/transcriptomics/shared_tools.py
lobster/agents/transcriptomics/state.py
lobster/agents/transcriptomics/transcriptomics_expert.py
lobster/cli_internal/__init__.py
lobster/cli_internal/commands/__init__.py
lobster/cli_internal/commands/output_adapter.py
lobster/cli_internal/commands/heavy/__init__.py
lobster/cli_internal/commands/heavy/data_commands.py
lobster/cli_internal/commands/heavy/modality_commands.py
lobster/cli_internal/commands/heavy/visualization_commands.py
lobster/cli_internal/commands/light/__init__.py
lobster/cli_internal/commands/light/config_commands.py
lobster/cli_internal/commands/light/file_commands.py
lobster/cli_internal/commands/light/metadata_commands.py
lobster/cli_internal/commands/light/pipeline_commands.py
lobster_ai-0.4.3.9.dist-info/licenses/LICENSE
lobster_ai-0.4.3.9.dist-info/METADATA
lobster_ai-0.4.3.9.dist-info/WHEEL
lobster_ai-0.4.3.9.dist-info/entry_points.txt
lobster_ai-0.4.3.9.dist-info/top_level.txt
lobster_ai-0.4.3.9.dist-info/RECORD
