Metadata-Version: 2.4
Name: lobster-ai
Version: 0.4.3.9
Summary: Multi-Agent Bioinformatics Analysis System powered by LangGraph
Home-page: https://github.com/the-omics-os/lobster-ai
Author: Omics-OS
Author-email: Omics-OS <info@omics-os.com>
License-Expression: AGPL-3.0-or-later
Project-URL: Homepage, https://www.omics-os.com
Project-URL: Bug Tracker, https://github.com/the-omics-os/lobster/issues
Project-URL: Documentation, https://github.com/the-omics-os/lobster.wiki
Project-URL: Source Code, https://github.com/the-omics-os/lobster
Keywords: bioinformatics,RNA-seq,single-cell,AI,machine-learning,data-analysis,genomics
Classifier: Development Status :: 4 - Beta
Classifier: Intended Audience :: Science/Research
Classifier: Intended Audience :: Healthcare Industry
Classifier: Operating System :: OS Independent
Classifier: Programming Language :: Python :: 3
Classifier: Programming Language :: Python :: 3.9
Classifier: Programming Language :: Python :: 3.10
Classifier: Programming Language :: Python :: 3.11
Classifier: Programming Language :: Python :: 3.12
Classifier: Topic :: Scientific/Engineering :: Bio-Informatics
Classifier: Topic :: Scientific/Engineering :: Artificial Intelligence
Classifier: Environment :: Console
Classifier: Framework :: FastAPI
Requires-Python: >=3.11
License-File: LICENSE
Requires-Dist: pandas>=1.5.0
Requires-Dist: numpy>=1.23.0
Requires-Dist: plotly>=5.0.0
Requires-Dist: rich>=12.0.0
Requires-Dist: typer>=0.7.0
Requires-Dist: python-dotenv>=1.0.0
Requires-Dist: langchain>=0.1.0
Requires-Dist: langchain-community>=0.0.10
Requires-Dist: langchain-aws>=0.1.0
Requires-Dist: langgraph>=1.0.5
Requires-Dist: langchain-google-genai>=4.1.2
Requires-Dist: llvmlite>=0.44.0
Requires-Dist: scipy>=1.10.0
Requires-Dist: scikit-learn>=1.3.0
Requires-Dist: anndata>=0.9.0
Requires-Dist: mudata>=0.2.0
Requires-Dist: biopython>=1.81
Requires-Dist: leidenalg>=0.9.0
Requires-Dist: igraph>=0.10.4
Requires-Dist: scrublet>=0.2.3
Requires-Dist: h5py>=3.9.0
Requires-Dist: tables>=3.8.0
Requires-Dist: statsmodels>=0.14.0
Requires-Dist: gseapy>=1.1.0
Requires-Dist: seaborn>=0.12.0
Requires-Dist: matplotlib>=3.7.0
Requires-Dist: kaleido>=0.2.0
Requires-Dist: openpyxl>=3.1.0
Requires-Dist: pyarrow>=12.0.0
Requires-Dist: pyreadr>=0.4.0
Requires-Dist: requests>=2.31.0
Requires-Dist: aiofiles>=23.0.0
Requires-Dist: xmltodict>=0.13.0
Requires-Dist: boto3>=1.26.0
Requires-Dist: pypdf2>=3.0.0
Requires-Dist: beautifulsoup4>=4.12.0
Requires-Dist: lxml>=4.9.0
Requires-Dist: fastapi>=0.100.0
Requires-Dist: uvicorn>=0.23.0
Requires-Dist: scikit-misc>=0.5.1
Requires-Dist: python-multipart>=0.0.20
Requires-Dist: GEOparse
Requires-Dist: packaging>=25.0
Requires-Dist: tabulate>=0.9.0
Requires-Dist: langfuse>=3.2.6
Requires-Dist: polars>=1.32.3
Requires-Dist: psutil>=7.0.0
Requires-Dist: scanpy>=1.11.4
Requires-Dist: pydeseq2>=0.5.2
Requires-Dist: prompt-toolkit>=3.0.52
Requires-Dist: langchain-anthropic>=0.3.20
Requires-Dist: responses>=0.25.8
Requires-Dist: nbformat>=5.9.0
Requires-Dist: papermill>=2.4.0
Requires-Dist: nbconvert>=7.0.0
Requires-Dist: jupytext>=1.15.0
Requires-Dist: docling>=2.60.0
Requires-Dist: docling-core>=2.50.0
Requires-Dist: redis>=6.4.0
Requires-Dist: pysradb>=2.5.1
Requires-Dist: rispy>=0.10.0
Requires-Dist: langchain-core>=0.3.79
Requires-Dist: textual>=6.7.1
Requires-Dist: langchain-ollama>=0.3.10
Requires-Dist: rapidfuzz>=3.14.3
Requires-Dist: cloudscraper>=1.2.71
Provides-Extra: ml
Requires-Dist: scvi-tools>=1.4.0; extra == "ml"
Requires-Dist: torch>=2.0.0; extra == "ml"
Requires-Dist: torchvision>=0.15.0; extra == "ml"
Provides-Extra: dev
Requires-Dist: pytest>=7.0.0; extra == "dev"
Requires-Dist: pytest-cov>=4.0.0; extra == "dev"
Requires-Dist: pytest-xdist>=3.0.0; extra == "dev"
Requires-Dist: pytest-asyncio>=0.21.0; extra == "dev"
Requires-Dist: pytest-mock>=3.10.0; extra == "dev"
Requires-Dist: pytest-benchmark>=4.0.0; extra == "dev"
Requires-Dist: pytest-timeout>=2.1.0; extra == "dev"
Requires-Dist: pytest-html>=3.2.0; extra == "dev"
Requires-Dist: pytest-json-report>=1.5.0; extra == "dev"
Requires-Dist: factory-boy>=3.2.0; extra == "dev"
Requires-Dist: responses>=0.23.0; extra == "dev"
Requires-Dist: httpretty>=1.1.4; extra == "dev"
Requires-Dist: freezegun>=1.2.0; extra == "dev"
Requires-Dist: faker>=19.0.0; extra == "dev"
Requires-Dist: moto>=4.1.0; extra == "dev"
Requires-Dist: fakeredis>=2.10.0; extra == "dev"
Requires-Dist: ftputil>=5.0.4; extra == "dev"
Requires-Dist: memory-profiler>=0.60.0; extra == "dev"
Requires-Dist: psutil>=5.9.0; extra == "dev"
Requires-Dist: black>=23.0.0; extra == "dev"
Requires-Dist: isort>=5.12.0; extra == "dev"
Requires-Dist: flake8>=6.0.0; extra == "dev"
Requires-Dist: pylint>=2.17.0; extra == "dev"
Requires-Dist: mypy>=1.0.0; extra == "dev"
Requires-Dist: bandit>=1.7.0; extra == "dev"
Requires-Dist: ruff>=0.0.300; extra == "dev"
Requires-Dist: responses>=0.25.8; extra == "dev"
Requires-Dist: pre-commit>=3.0.0; extra == "dev"
Requires-Dist: bumpversion>=0.6.0; extra == "dev"
Requires-Dist: twine>=4.0.0; extra == "dev"
Requires-Dist: build>=0.10.0; extra == "dev"
Requires-Dist: mkdocs>=1.5.0; extra == "dev"
Requires-Dist: mkdocs-material>=9.0.0; extra == "dev"
Requires-Dist: langfuse>=2.0.0; extra == "dev"
Requires-Dist: tabulate>=0.9.0; extra == "dev"
Provides-Extra: all
Requires-Dist: scvi-tools>=1.4.0; extra == "all"
Requires-Dist: torch>=2.0.0; extra == "all"
Requires-Dist: torchvision>=0.15.0; extra == "all"
Requires-Dist: pytest>=7.0.0; extra == "all"
Requires-Dist: pytest-cov>=4.0.0; extra == "all"
Requires-Dist: pytest-xdist>=3.0.0; extra == "all"
Requires-Dist: pytest-asyncio>=0.20.0; extra == "all"
Requires-Dist: black>=23.0.0; extra == "all"
Requires-Dist: isort>=5.12.0; extra == "all"
Requires-Dist: flake8>=6.0.0; extra == "all"
Requires-Dist: pylint>=2.17.0; extra == "all"
Requires-Dist: mypy>=1.0.0; extra == "all"
Requires-Dist: bandit>=1.7.0; extra == "all"
Requires-Dist: pre-commit>=3.0.0; extra == "all"
Requires-Dist: bumpversion>=0.6.0; extra == "all"
Requires-Dist: twine>=4.0.0; extra == "all"
Requires-Dist: build>=0.10.0; extra == "all"
Requires-Dist: mkdocs>=1.5.0; extra == "all"
Requires-Dist: mkdocs-material>=9.0.0; extra == "all"
Requires-Dist: langfuse>=2.0.0; extra == "all"
Requires-Dist: tabulate>=0.9.0; extra == "all"
Dynamic: author
Dynamic: home-page
Dynamic: license-file
Dynamic: requires-python
